{
  "Article image": "Article image",
  "{text}": "{text}",
  "Аватар пользователя": "Аватар пользователя",
  "Авторизация": "Авторизация",
  "Алфавиту": "Алфавиту",
  "Валюта": "Валюта",
  "Вернуться к списку": "Вернуться к списку",
  "Возраст": "Возраст",
  "Войти": "Войти",
  "Выйти": "Выйти",
  "Главная": "Главная",
  "Главная страница": "Главная страница",
  "Город": "Город",
  "Данные не указаны": "Данные не указаны",
  "Дате": "Дате",
  "Имя": "Имя",
  "Имя и фамилия обязательны": "Имя и фамилия обязательны",
  "Имя пользователя": "Имя пользователя",
  "Комментарии": "Комментарии",
  "Комментарии отсутствуют": "Комментарии отсутствуют",
  "Комментарий": "Комментарий",
  "Логин": "Логин",
  "Неверный логин или парль": "Неверный логин или парль",
  "Неверный логин или пароль": "Неверный логин или пароль",
  "Некорректный возраст": "Некорректный возраст",
  "О нас": "О нас",
  "Обновите страницу или попробуйте позже": "Обновите страницу или попробуйте позже",
  "Обновить страницу": "Обновить страницу",
  "Отменить": "Отменить",
  "Отправить": "Отправить",
  "Ошибка 404": "Ошибка 404",
  "ПО": "ПО",
  "Пароль": "Пароль",
  "По": "По",
  "Подтвердить": "Подтвердить",
  "Поиск": "Поиск",
  "Произошла непредвиденная ошибка": "Произошла непредвиденная ошибка",
  "Произошла ошибка при загрузке профиля": "Произошла ошибка при загрузке профиля",
  "Произошла ошибка при загрузке статьи": "Произошла ошибка при загрузке статьи",
  "Просмотрам": "Просмотрам",
  "Профиль": "Профиль",
  "Редактировать": "Редактировать",
  "Рекомендуем": "Рекомендуем",
  "Свернуть": "Свернуть",
  "Серверная ошибка": "Серверная ошибка",
  "Сортировать По": "Сортировать По",
  "Сортировать по": "Сортировать по",
  "Ссылка на аватар": "Ссылка на аватар",
  "Статьи": "Статьи",
  "Статьи не найдены": "Статьи не найдены",
  "Статья не найдена": "Статья не найдена",
  "Страна": "Страна",
  "Страница всех статей": "Страница всех статей",
  "Страница не найдена": "Страница не найдена",
  "Страница профиля": "Страница профиля",
  "Страница статьи": "Страница статьи",
  "Фамилия": "Фамилия",
  "Читать далее": {
    "": {
      "": {
        "": ""
      }
    }
  },
  "Язык": "Язык",
  "возрастанию": "возрастанию",
  "по": "по",
  "тест плагина": "Test Plugin",
  "убыванию": "убыванию"
}
